pyapply/VERSION
pyapply/__init__.py
pyapply/__main__.py
pyapply/utils.py
pyapply/version.py
pyapply/coverletters/__init__.py
pyapply/coverletters/plainDocV1.py
pyapply/coverletters/plainV1.py
pyapply/userdatafiles/__init__.py
pyapply/workflows/__init__.py
pyapply/workflows/asujobs.py
pyapply-0.1.6.dist-info/LICENSE
pyapply-0.1.6.dist-info/METADATA
pyapply-0.1.6.dist-info/WHEEL
pyapply-0.1.6.dist-info/entry_points.txt
pyapply-0.1.6.dist-info/top_level.txt
pyapply-0.1.6.dist-info/RECORD
