Metadata-Version: 2.1
Name: pyapply
Version: 0.1.6
Summary: Tool to automate coverletter generation (and much more)
Home-page: https://github.com/kirtansoni/pyapply
Author: Kirtan Soni
Author-email: 1kirtansoni@gmail.com
Requires-Python: >=3.5
License-File: LICENSE
Requires-Dist: docx ==0.2.4
Requires-Dist: click ==8.1.7
Requires-Dist: openai ==1.3.6
Requires-Dist: pyperclip ==1.8.2
Requires-Dist: python-dotenv ==1.0.0
Requires-Dist: reportlab ==4.0.7
Requires-Dist: click-help-colors ==0.9.4
